{"frames": [

{
	"filename": "chick_E_00001.png",
	"frame": {"x":400,"y":240,"w":80,"h":80},
	"rotated": false,
	"trimmed": false,
	"spriteSourceSize": {"x":0,"y":0,"w":80,"h":80},
	"sourceSize": {"w":80,"h":80}
},
{
	"filename": "chick_E_00003.png",
	"frame": {"x":320,"y":240,"w":80,"h":80},
	"rotated": false,
	"trimmed": false,
	"spriteSourceSize": {"x":0,"y":0,"w":80,"h":80},
	"sourceSize": {"w":80,"h":80}
},
{
	"filename": "chick_E_00005.png",
	"frame": {"x":240,"y":400,"w":80,"h":80},
	"rotated": false,
	"trimmed": false,
	"spriteSourceSize": {"x":0,"y":0,"w":80,"h":80},
	"sourceSize": {"w":80,"h":80}
},
{
	"filename": "chick_E_00007.png",
	"frame": {"x":240,"y":320,"w":80,"h":80},
	"rotated": false,
	"trimmed": false,
	"spriteSourceSize": {"x":0,"y":0,"w":80,"h":80},
	"sourceSize": {"w":80,"h":80}
},
{
	"filename": "chick_E_00009.png",
	"frame": {"x":240,"y":240,"w":80,"h":80},
	"rotated": false,
	"trimmed": false,
	"spriteSourceSize": {"x":0,"y":0,"w":80,"h":80},
	"sourceSize": {"w":80,"h":80}
},
{
	"filename": "chick_E_00011.png",
	"frame": {"x":240,"y":320,"w":80,"h":80},
	"rotated": false,
	"trimmed": false,
	"spriteSourceSize": {"x":0,"y":0,"w":80,"h":80},
	"sourceSize": {"w":80,"h":80}
},
{
	"filename": "chick_E_00013.png",
	"frame": {"x":240,"y":400,"w":80,"h":80},
	"rotated": false,
	"trimmed": false,
	"spriteSourceSize": {"x":0,"y":0,"w":80,"h":80},
	"sourceSize": {"w":80,"h":80}
},
{
	"filename": "chick_E_00015.png",
	"frame": {"x":320,"y":240,"w":80,"h":80},
	"rotated": false,
	"trimmed": false,
	"spriteSourceSize": {"x":0,"y":0,"w":80,"h":80},
	"sourceSize": {"w":80,"h":80}
},
{
	"filename": "chick_E_00017.png",
	"frame": {"x":400,"y":240,"w":80,"h":80},
	"rotated": false,
	"trimmed": false,
	"spriteSourceSize": {"x":0,"y":0,"w":80,"h":80},
	"sourceSize": {"w":80,"h":80}
},
{
	"filename": "chick_E_00019.png",
	"frame": {"x":400,"y":160,"w":80,"h":80},
	"rotated": false,
	"trimmed": false,
	"spriteSourceSize": {"x":0,"y":0,"w":80,"h":80},
	"sourceSize": {"w":80,"h":80}
},
{
	"filename": "chick_E_00021.png",
	"frame": {"x":320,"y":160,"w":80,"h":80},
	"rotated": false,
	"trimmed": false,
	"spriteSourceSize": {"x":0,"y":0,"w":80,"h":80},
	"sourceSize": {"w":80,"h":80}
},
{
	"filename": "chick_E_00023.png",
	"frame": {"x":240,"y":160,"w":80,"h":80},
	"rotated": false,
	"trimmed": false,
	"spriteSourceSize": {"x":0,"y":0,"w":80,"h":80},
	"sourceSize": {"w":80,"h":80}
},
{
	"filename": "chick_E_00025.png",
	"frame": {"x":160,"y":400,"w":80,"h":80},
	"rotated": false,
	"trimmed": false,
	"spriteSourceSize": {"x":0,"y":0,"w":80,"h":80},
	"sourceSize": {"w":80,"h":80}
},
{
	"filename": "chick_E_00027.png",
	"frame": {"x":160,"y":320,"w":80,"h":80},
	"rotated": false,
	"trimmed": false,
	"spriteSourceSize": {"x":0,"y":0,"w":80,"h":80},
	"sourceSize": {"w":80,"h":80}
},
{
	"filename": "chick_E_00029.png",
	"frame": {"x":160,"y":240,"w":80,"h":80},
	"rotated": false,
	"trimmed": false,
	"spriteSourceSize": {"x":0,"y":0,"w":80,"h":80},
	"sourceSize": {"w":80,"h":80}
},
{
	"filename": "chick_E_00031.png",
	"frame": {"x":160,"y":160,"w":80,"h":80},
	"rotated": false,
	"trimmed": false,
	"spriteSourceSize": {"x":0,"y":0,"w":80,"h":80},
	"sourceSize": {"w":80,"h":80}
},
{
	"filename": "chick_E_00033.png",
	"frame": {"x":400,"y":80,"w":80,"h":80},
	"rotated": false,
	"trimmed": false,
	"spriteSourceSize": {"x":0,"y":0,"w":80,"h":80},
	"sourceSize": {"w":80,"h":80}
},
{
	"filename": "chick_E_00035.png",
	"frame": {"x":320,"y":80,"w":80,"h":80},
	"rotated": false,
	"trimmed": false,
	"spriteSourceSize": {"x":0,"y":0,"w":80,"h":80},
	"sourceSize": {"w":80,"h":80}
},
{
	"filename": "chick_E_00037.png",
	"frame": {"x":240,"y":80,"w":80,"h":80},
	"rotated": false,
	"trimmed": false,
	"spriteSourceSize": {"x":0,"y":0,"w":80,"h":80},
	"sourceSize": {"w":80,"h":80}
},
{
	"filename": "chick_E_00039.png",
	"frame": {"x":160,"y":80,"w":80,"h":80},
	"rotated": false,
	"trimmed": false,
	"spriteSourceSize": {"x":0,"y":0,"w":80,"h":80},
	"sourceSize": {"w":80,"h":80}
},
{
	"filename": "chick_E_00041.png",
	"frame": {"x":80,"y":400,"w":80,"h":80},
	"rotated": false,
	"trimmed": false,
	"spriteSourceSize": {"x":0,"y":0,"w":80,"h":80},
	"sourceSize": {"w":80,"h":80}
},
{
	"filename": "chick_E_00043.png",
	"frame": {"x":80,"y":400,"w":80,"h":80},
	"rotated": false,
	"trimmed": false,
	"spriteSourceSize": {"x":0,"y":0,"w":80,"h":80},
	"sourceSize": {"w":80,"h":80}
},
{
	"filename": "chick_E_00045.png",
	"frame": {"x":160,"y":80,"w":80,"h":80},
	"rotated": false,
	"trimmed": false,
	"spriteSourceSize": {"x":0,"y":0,"w":80,"h":80},
	"sourceSize": {"w":80,"h":80}
},
{
	"filename": "chick_E_00047.png",
	"frame": {"x":80,"y":320,"w":80,"h":80},
	"rotated": false,
	"trimmed": false,
	"spriteSourceSize": {"x":0,"y":0,"w":80,"h":80},
	"sourceSize": {"w":80,"h":80}
},
{
	"filename": "chick_E_00049.png",
	"frame": {"x":80,"y":240,"w":80,"h":80},
	"rotated": false,
	"trimmed": false,
	"spriteSourceSize": {"x":0,"y":0,"w":80,"h":80},
	"sourceSize": {"w":80,"h":80}
},
{
	"filename": "chick_E_00051.png",
	"frame": {"x":400,"y":80,"w":80,"h":80},
	"rotated": false,
	"trimmed": false,
	"spriteSourceSize": {"x":0,"y":0,"w":80,"h":80},
	"sourceSize": {"w":80,"h":80}
},
{
	"filename": "chick_E_00053.png",
	"frame": {"x":80,"y":160,"w":80,"h":80},
	"rotated": false,
	"trimmed": false,
	"spriteSourceSize": {"x":0,"y":0,"w":80,"h":80},
	"sourceSize": {"w":80,"h":80}
},
{
	"filename": "chick_E_00055.png",
	"frame": {"x":80,"y":80,"w":80,"h":80},
	"rotated": false,
	"trimmed": false,
	"spriteSourceSize": {"x":0,"y":0,"w":80,"h":80},
	"sourceSize": {"w":80,"h":80}
},
{
	"filename": "chick_E_00057.png",
	"frame": {"x":400,"y":0,"w":80,"h":80},
	"rotated": false,
	"trimmed": false,
	"spriteSourceSize": {"x":0,"y":0,"w":80,"h":80},
	"sourceSize": {"w":80,"h":80}
},
{
	"filename": "chick_E_00059.png",
	"frame": {"x":320,"y":0,"w":80,"h":80},
	"rotated": false,
	"trimmed": false,
	"spriteSourceSize": {"x":0,"y":0,"w":80,"h":80},
	"sourceSize": {"w":80,"h":80}
},
{
	"filename": "chick_E_00061.png",
	"frame": {"x":240,"y":0,"w":80,"h":80},
	"rotated": false,
	"trimmed": false,
	"spriteSourceSize": {"x":0,"y":0,"w":80,"h":80},
	"sourceSize": {"w":80,"h":80}
},
{
	"filename": "chick_E_00063.png",
	"frame": {"x":160,"y":0,"w":80,"h":80},
	"rotated": false,
	"trimmed": false,
	"spriteSourceSize": {"x":0,"y":0,"w":80,"h":80},
	"sourceSize": {"w":80,"h":80}
},
{
	"filename": "chick_E_00065.png",
	"frame": {"x":400,"y":80,"w":80,"h":80},
	"rotated": false,
	"trimmed": false,
	"spriteSourceSize": {"x":0,"y":0,"w":80,"h":80},
	"sourceSize": {"w":80,"h":80}
},
{
	"filename": "chick_E_00067.png",
	"frame": {"x":80,"y":0,"w":80,"h":80},
	"rotated": false,
	"trimmed": false,
	"spriteSourceSize": {"x":0,"y":0,"w":80,"h":80},
	"sourceSize": {"w":80,"h":80}
},
{
	"filename": "chick_E_00069.png",
	"frame": {"x":0,"y":400,"w":80,"h":80},
	"rotated": false,
	"trimmed": false,
	"spriteSourceSize": {"x":0,"y":0,"w":80,"h":80},
	"sourceSize": {"w":80,"h":80}
},
{
	"filename": "chick_E_00071.png",
	"frame": {"x":0,"y":320,"w":80,"h":80},
	"rotated": false,
	"trimmed": false,
	"spriteSourceSize": {"x":0,"y":0,"w":80,"h":80},
	"sourceSize": {"w":80,"h":80}
},
{
	"filename": "chick_E_00073.png",
	"frame": {"x":0,"y":240,"w":80,"h":80},
	"rotated": false,
	"trimmed": false,
	"spriteSourceSize": {"x":0,"y":0,"w":80,"h":80},
	"sourceSize": {"w":80,"h":80}
},
{
	"filename": "chick_E_00075.png",
	"frame": {"x":0,"y":160,"w":80,"h":80},
	"rotated": false,
	"trimmed": false,
	"spriteSourceSize": {"x":0,"y":0,"w":80,"h":80},
	"sourceSize": {"w":80,"h":80}
},
{
	"filename": "chick_E_00077.png",
	"frame": {"x":0,"y":80,"w":80,"h":80},
	"rotated": false,
	"trimmed": false,
	"spriteSourceSize": {"x":0,"y":0,"w":80,"h":80},
	"sourceSize": {"w":80,"h":80}
},
{
	"filename": "chick_E_00079.png",
	"frame": {"x":0,"y":0,"w":80,"h":80},
	"rotated": false,
	"trimmed": false,
	"spriteSourceSize": {"x":0,"y":0,"w":80,"h":80},
	"sourceSize": {"w":80,"h":80}
}],
"meta": {
	"app": "http://www.codeandweb.com/texturepacker ",
	"version": "1.0",
	"image": "decorChick5.png",
	"format": "RGBA8888",
	"size": {"w":480,"h":480},
	"scale": "1",
	"smartupdate": "$TexturePacker:SmartUpdate:bb98b4c7bfc7929c709ca2398e0dd64e:1/1$"
}
}
